pixel_invaders/__init__.py
pixel_invaders/boost.py
pixel_invaders/boosts_manager.py
pixel_invaders/boss.py
pixel_invaders/boss_2.py
pixel_invaders/enemies_manager.py
pixel_invaders/enemy.py
pixel_invaders/enemy_bullet.py
pixel_invaders/main.py
pixel_invaders/menu.py
pixel_invaders/player.py
pixel_invaders/player_bullet.py
pixel_invaders/shooting_manager.py
pixel_invaders/starfield.py
pixel_invaders/assets/images/boosts_spritesheet.png
pixel_invaders/assets/images/enemies_spritesheet.png
pixel_invaders/assets/images/player_spritesheet.png
pixel_invaders/data/stats.json
pixel_invaders/data/waves.json
pixel_invaders-1.0.0.dist-info/LICENSE
pixel_invaders-1.0.0.dist-info/METADATA
pixel_invaders-1.0.0.dist-info/WHEEL
pixel_invaders-1.0.0.dist-info/entry_points.txt
pixel_invaders-1.0.0.dist-info/top_level.txt
pixel_invaders-1.0.0.dist-info/RECORD
