Metadata-Version: 2.2
Name: pixel-invaders
Version: 1.0.0
Summary: A fun little retro pixel art game where you defend the galaxy against an alien invasion.
Home-page: https://github.com/LeoLeman555/Pixel_Invaders
Author: Léo Leman
Classifier: Programming Language :: Python :: 3
Classifier: License :: OSI Approved :: MIT License
Classifier: Operating System :: OS Independent
Requires-Python: >=3.11
License-File: LICENSE
Requires-Dist: pyxel
Dynamic: author
Dynamic: classifier
Dynamic: description
Dynamic: description-content-type
Dynamic: home-page
Dynamic: requires-dist
Dynamic: requires-python
Dynamic: summary
